aws_iam_login/__init__.py
aws_iam_login/access_key.py
aws_iam_login/actions/__init__.py
aws_iam_login/actions/action.py
aws_iam_login/actions/initialize_configuration.py
aws_iam_login/actions/rotate_access_keys.py
aws_iam_login/application_context.py
aws_iam_login/aws_config.py
aws_iam_login/credentials.py
aws_iam_login/observer.py
aws_iam_login/temp_credentials.py
aws_iam_login-0.3.6.dist-info/LICENSE.txt
aws_iam_login-0.3.6.dist-info/METADATA
aws_iam_login-0.3.6.dist-info/WHEEL
aws_iam_login-0.3.6.dist-info/entry_points.txt
aws_iam_login-0.3.6.dist-info/RECORD
