Metadata-Version: 2.1
Name: aws-iam-login
Version: 0.3.6
Summary: Configures STS credentials using a MFA authenticated session.
License: Apache2
Author: Joris Conijn
Author-email: joris@conijnonline.nl
Requires-Python: >=3.8,<4.0
Classifier: License :: Other/Proprietary License
Classifier: Programming Language :: Python :: 3
Classifier: Programming Language :: Python :: 3.8
Classifier: Programming Language :: Python :: 3.9
Classifier: Programming Language :: Python :: 3.10
Classifier: Programming Language :: Python :: 3.11
Classifier: Programming Language :: Python :: 3.12
Requires-Dist: boto3 (>=1.28.19,<2.0.0)
Requires-Dist: click (>=8.1.6,<9.0.0)
